orator/__init__.py
orator/launch.py
orator/agents/__init__.py
orator/agents/lite.py
orator/chains/__init__.py
orator/chains/chitchat.py
orator/chains/code.py
orator/chains/docs.py
orator/chains/query_router.py
orator/vectorstores/__init__.py
orator/vectorstores/chroma.py
redcoast_orator-0.0.1.dist-info/LICENSE
redcoast_orator-0.0.1.dist-info/METADATA
redcoast_orator-0.0.1.dist-info/WHEEL
redcoast_orator-0.0.1.dist-info/top_level.txt
redcoast_orator-0.0.1.dist-info/RECORD
