Metadata-Version: 2.1
Name: redcoast-orator
Version: 0.0.1
Author: Redcoast AI Group
License-File: LICENSE
Requires-Dist: torch
Requires-Dist: transformers
Requires-Dist: gradio
Requires-Dist: pyMuPDF
Requires-Dist: langchain ==0.2.16
Requires-Dist: langchain-chroma ==0.1.3
Requires-Dist: langchain-community ==0.2.16
Requires-Dist: langchain-core ==0.2.38
Requires-Dist: langchain-openai ==0.1.23
Requires-Dist: langgraph ==0.2.19
Requires-Dist: loguru
Requires-Dist: GitPython
